odoo/addons/website_menu_permission/README.rst
odoo/addons/website_menu_permission/__init__.py
odoo/addons/website_menu_permission/__manifest__.py
odoo/addons/website_menu_permission/i18n/website_menu_permission.pot
odoo/addons/website_menu_permission/models/__init__.py
odoo/addons/website_menu_permission/models/website_menu.py
odoo/addons/website_menu_permission/readme/CONTRIBUTORS.rst
odoo/addons/website_menu_permission/readme/DESCRIPTION.rst
odoo/addons/website_menu_permission/readme/USAGE.rst
odoo/addons/website_menu_permission/security/record_rules.xml
odoo/addons/website_menu_permission/static/description/icon.png
odoo/addons/website_menu_permission/static/description/index.html
odoo/addons/website_menu_permission/tests/__init__.py
odoo/addons/website_menu_permission/tests/test_menu_perm.py
odoo/addons/website_menu_permission/views/website_views.xml
odoo11_addon_website_menu_permission-11.0.1.0.0.99.dev5.dist-info/METADATA
odoo11_addon_website_menu_permission-11.0.1.0.0.99.dev5.dist-info/WHEEL
odoo11_addon_website_menu_permission-11.0.1.0.0.99.dev5.dist-info/top_level.txt
odoo11_addon_website_menu_permission-11.0.1.0.0.99.dev5.dist-info/RECORD
